road_collisions_ireland/__init__.py
road_collisions_ireland/constants.py
road_collisions_ireland/bin/__init__.py
road_collisions_ireland/bin/load.py
road_collisions_ireland/bin/pull_new.py
road_collisions_ireland/bin/raw_cleaner.py
road_collisions_ireland/models/__init__.py
road_collisions_ireland/models/collision.py
road_collisions_ireland/resources/ireland/ireland.csv.tgz
road_collisions_ireland-0.0.11.dist-info/LICENSE
road_collisions_ireland-0.0.11.dist-info/METADATA
road_collisions_ireland-0.0.11.dist-info/WHEEL
road_collisions_ireland-0.0.11.dist-info/entry_points.txt
road_collisions_ireland-0.0.11.dist-info/top_level.txt
road_collisions_ireland-0.0.11.dist-info/RECORD
